odoo/addons/ssi_project_outsource_work_acceptance/README.rst
odoo/addons/ssi_project_outsource_work_acceptance/__init__.py
odoo/addons/ssi_project_outsource_work_acceptance/__manifest__.py
odoo/addons/ssi_project_outsource_work_acceptance/data/approval_template_data.xml
odoo/addons/ssi_project_outsource_work_acceptance/data/ir_sequence_data.xml
odoo/addons/ssi_project_outsource_work_acceptance/data/policy_template_data.xml
odoo/addons/ssi_project_outsource_work_acceptance/data/sequence_template_data.xml
odoo/addons/ssi_project_outsource_work_acceptance/models/__init__.py
odoo/addons/ssi_project_outsource_work_acceptance/models/project_outsource_work_acceptance.py
odoo/addons/ssi_project_outsource_work_acceptance/security/ir.model.access.csv
odoo/addons/ssi_project_outsource_work_acceptance/security/ir_module_category_data.xml
odoo/addons/ssi_project_outsource_work_acceptance/security/ir_rule_data.xml
odoo/addons/ssi_project_outsource_work_acceptance/security/res_group_data.xml
odoo/addons/ssi_project_outsource_work_acceptance/static/description/icon.png
odoo/addons/ssi_project_outsource_work_acceptance/views/project_outsource_work_acceptance_views.xml
odoo14_addon_ssi_project_outsource_work_acceptance-14.0.1.2.0.dist-info/METADATA
odoo14_addon_ssi_project_outsource_work_acceptance-14.0.1.2.0.dist-info/WHEEL
odoo14_addon_ssi_project_outsource_work_acceptance-14.0.1.2.0.dist-info/top_level.txt
odoo14_addon_ssi_project_outsource_work_acceptance-14.0.1.2.0.dist-info/RECORD
